[
  {
    "execution_time": "2025-10-08T13:06:47.915364",
    "total_apps": 7,
    "results": [
      {
        "name": "TODO アプリ",
        "url": "https://appsimpletodo-nrzgxmanzr42p2bu5ckfqr.streamlit.app",
        "timestamp": "2025-10-08T13:06:23.318423",
        "attempts": 1,
        "status": "ALREADY_RUNNING",
        "message": "App is already running"
      }
    ]
  },
  {
    "execution_time": "2025-10-08T17:08:25.375066",
    "total_apps": 7,
    "results": [
      {
        "name": "TODO アプリ",
        "url": "https://appsimpletodo-nrzgxmanzr42p2bu5ckfqr.streamlit.app",
        "timestamp": "2025-10-08T17:08:00.779041",
        "attempts": 1,
        "status": "ALREADY_RUNNING",
        "message": "App is already running"
      }
    ]
  },
  {
    "execution_time": "2025-10-08T21:10:02.252027",
    "total_apps": 7,
    "results": [
      {
        "name": "TODO アプリ",
        "url": "https://appsimpletodo-nrzgxmanzr42p2bu5ckfqr.streamlit.app",
        "timestamp": "2025-10-08T21:09:37.638494",
        "attempts": 1,
        "status": "ALREADY_RUNNING",
        "message": "App is already running"
      }
    ]
  },
  {
    "execution_time": "2025-10-09T01:06:48.963338",
    "total_apps": 7,
    "results": [
      {
        "name": "TODO アプリ",
        "url": "https://appsimpletodo-nrzgxmanzr42p2bu5ckfqr.streamlit.app",
        "timestamp": "2025-10-09T01:06:24.347436",
        "attempts": 1,
        "status": "ALREADY_RUNNING",
        "message": "App is already running"
      }
    ]
  },
  {
    "execution_time": "2025-10-09T05:06:24.001119",
    "total_apps": 7,
    "results": [
      {
        "name": "TODO アプリ",
        "url": "https://appsimpletodo-nrzgxmanzr42p2bu5ckfqr.streamlit.app",
        "timestamp": "2025-10-09T05:05:59.481357",
        "attempts": 1,
        "status": "ALREADY_RUNNING",
        "message": "App is already running"
      }
    ]
  },
  {
    "execution_time": "2025-10-09T09:19:47.888623",
    "total_apps": 7,
    "results": [
      {
        "name": "TODO アプリ",
        "url": "https://appsimpletodo-nrzgxmanzr42p2bu5ckfqr.streamlit.app",
        "timestamp": "2025-10-09T09:19:23.363359",
        "attempts": 1,
        "status": "ALREADY_RUNNING",
        "message": "App is already running"
      }
    ]
  },
  {
    "execution_time": "2025-10-09T13:06:47.644745",
    "total_apps": 7,
    "results": [
      {
        "name": "TODO アプリ",
        "url": "https://appsimpletodo-nrzgxmanzr42p2bu5ckfqr.streamlit.app",
        "timestamp": "2025-10-09T13:06:23.190853",
        "attempts": 1,
        "status": "ALREADY_RUNNING",
        "message": "App is already running"
      }
    ]
  },
  {
    "execution_time": "2025-10-09T17:07:53.214135",
    "total_apps": 7,
    "results": [
      {
        "name": "TODO アプリ",
        "url": "https://appsimpletodo-nrzgxmanzr42p2bu5ckfqr.streamlit.app",
        "timestamp": "2025-10-09T17:07:28.353812",
        "attempts": 1,
        "status": "ALREADY_RUNNING",
        "message": "App is already running"
      }
    ]
  },
  {
    "execution_time": "2025-10-09T21:09:25.120592",
    "total_apps": 7,
    "results": [
      {
        "name": "TODO アプリ",
        "url": "https://appsimpletodo-nrzgxmanzr42p2bu5ckfqr.streamlit.app",
        "timestamp": "2025-10-09T21:09:00.553131",
        "attempts": 1,
        "status": "ALREADY_RUNNING",
        "message": "App is already running"
      }
    ]
  },
  {
    "execution_time": "2025-10-10T01:07:44.902246",
    "total_apps": 7,
    "results": [
      {
        "name": "TODO アプリ",
        "url": "https://appsimpletodo-nrzgxmanzr42p2bu5ckfqr.streamlit.app",
        "timestamp": "2025-10-10T01:07:20.386812",
        "attempts": 1,
        "status": "ALREADY_RUNNING",
        "message": "App is already running"
      }
    ]
  }
]