[
  {
    "execution_time": "2026-03-22T17:10:31.139109",
    "total_apps": 7,
    "results": [
      {
        "name": "TODO アプリ",
        "url": "https://appsimpletodo-nrzgxmanzr42p2bu5ckfqr.streamlit.app",
        "timestamp": "2026-03-22T17:10:06.498325",
        "attempts": 1,
        "status": "ALREADY_RUNNING",
        "message": "App is already running"
      }
    ]
  },
  {
    "execution_time": "2026-03-22T21:11:13.476455",
    "total_apps": 7,
    "results": [
      {
        "name": "TODO アプリ",
        "url": "https://appsimpletodo-nrzgxmanzr42p2bu5ckfqr.streamlit.app",
        "timestamp": "2026-03-22T21:10:48.419734",
        "attempts": 1,
        "status": "ALREADY_RUNNING",
        "message": "App is already running"
      }
    ]
  },
  {
    "execution_time": "2026-03-23T01:08:33.859554",
    "total_apps": 7,
    "results": [
      {
        "name": "TODO アプリ",
        "url": "https://appsimpletodo-nrzgxmanzr42p2bu5ckfqr.streamlit.app",
        "timestamp": "2026-03-23T01:08:09.308629",
        "attempts": 1,
        "status": "ALREADY_RUNNING",
        "message": "App is already running"
      }
    ]
  },
  {
    "execution_time": "2026-03-23T05:07:02.473438",
    "total_apps": 7,
    "results": [
      {
        "name": "TODO アプリ",
        "url": "https://appsimpletodo-nrzgxmanzr42p2bu5ckfqr.streamlit.app",
        "timestamp": "2026-03-23T05:06:37.288244",
        "attempts": 1,
        "status": "ALREADY_RUNNING",
        "message": "App is already running"
      }
    ]
  },
  {
    "execution_time": "2026-03-23T09:32:10.887633",
    "total_apps": 7,
    "results": [
      {
        "name": "TODO アプリ",
        "url": "https://appsimpletodo-nrzgxmanzr42p2bu5ckfqr.streamlit.app",
        "timestamp": "2026-03-23T09:31:45.895015",
        "attempts": 1,
        "status": "ALREADY_RUNNING",
        "message": "App is already running"
      }
    ]
  },
  {
    "execution_time": "2026-03-23T13:47:41.765542",
    "total_apps": 7,
    "results": [
      {
        "name": "TODO アプリ",
        "url": "https://appsimpletodo-nrzgxmanzr42p2bu5ckfqr.streamlit.app",
        "timestamp": "2026-03-23T13:47:17.031457",
        "attempts": 1,
        "status": "ALREADY_RUNNING",
        "message": "App is already running"
      }
    ]
  },
  {
    "execution_time": "2026-03-23T17:22:52.002590",
    "total_apps": 7,
    "results": [
      {
        "name": "TODO アプリ",
        "url": "https://appsimpletodo-nrzgxmanzr42p2bu5ckfqr.streamlit.app",
        "timestamp": "2026-03-23T17:22:27.085916",
        "attempts": 1,
        "status": "ALREADY_RUNNING",
        "message": "App is already running"
      }
    ]
  },
  {
    "execution_time": "2026-03-23T21:19:22.040113",
    "total_apps": 7,
    "results": [
      {
        "name": "TODO アプリ",
        "url": "https://appsimpletodo-nrzgxmanzr42p2bu5ckfqr.streamlit.app",
        "timestamp": "2026-03-23T21:18:57.396738",
        "attempts": 1,
        "status": "ALREADY_RUNNING",
        "message": "App is already running"
      }
    ]
  },
  {
    "execution_time": "2026-03-24T01:22:56.823733",
    "total_apps": 7,
    "results": [
      {
        "name": "TODO アプリ",
        "url": "https://appsimpletodo-nrzgxmanzr42p2bu5ckfqr.streamlit.app",
        "timestamp": "2026-03-24T01:22:32.069267",
        "attempts": 1,
        "status": "ALREADY_RUNNING",
        "message": "App is already running"
      }
    ]
  },
  {
    "execution_time": "2026-03-24T05:15:13.762562",
    "total_apps": 7,
    "results": [
      {
        "name": "TODO アプリ",
        "url": "https://appsimpletodo-nrzgxmanzr42p2bu5ckfqr.streamlit.app",
        "timestamp": "2026-03-24T05:14:48.377023",
        "attempts": 1,
        "status": "ALREADY_RUNNING",
        "message": "App is already running"
      }
    ]
  }
]