[
  {
    "execution_time": "2025-12-26T09:22:37.150564",
    "total_apps": 7,
    "results": [
      {
        "name": "TODO アプリ",
        "url": "https://appsimpletodo-nrzgxmanzr42p2bu5ckfqr.streamlit.app",
        "timestamp": "2025-12-26T09:22:12.628896",
        "attempts": 1,
        "status": "ALREADY_RUNNING",
        "message": "App is already running"
      }
    ]
  },
  {
    "execution_time": "2025-12-26T13:16:46.212232",
    "total_apps": 7,
    "results": [
      {
        "name": "TODO アプリ",
        "url": "https://appsimpletodo-nrzgxmanzr42p2bu5ckfqr.streamlit.app",
        "timestamp": "2025-12-26T13:16:21.589827",
        "attempts": 1,
        "status": "ALREADY_RUNNING",
        "message": "App is already running"
      }
    ]
  },
  {
    "execution_time": "2025-12-26T17:07:44.802041",
    "total_apps": 7,
    "results": [
      {
        "name": "TODO アプリ",
        "url": "https://appsimpletodo-nrzgxmanzr42p2bu5ckfqr.streamlit.app",
        "timestamp": "2025-12-26T17:07:20.316910",
        "attempts": 1,
        "status": "ALREADY_RUNNING",
        "message": "App is already running"
      }
    ]
  },
  {
    "execution_time": "2025-12-26T21:09:26.714537",
    "total_apps": 7,
    "results": [
      {
        "name": "TODO アプリ",
        "url": "https://appsimpletodo-nrzgxmanzr42p2bu5ckfqr.streamlit.app",
        "timestamp": "2025-12-26T21:09:02.151291",
        "attempts": 1,
        "status": "ALREADY_RUNNING",
        "message": "App is already running"
      }
    ]
  },
  {
    "execution_time": "2025-12-27T01:06:18.906028",
    "total_apps": 7,
    "results": [
      {
        "name": "TODO アプリ",
        "url": "https://appsimpletodo-nrzgxmanzr42p2bu5ckfqr.streamlit.app",
        "timestamp": "2025-12-27T01:05:54.388079",
        "attempts": 1,
        "status": "ALREADY_RUNNING",
        "message": "App is already running"
      }
    ]
  },
  {
    "execution_time": "2025-12-27T05:05:53.339491",
    "total_apps": 7,
    "results": [
      {
        "name": "TODO アプリ",
        "url": "https://appsimpletodo-nrzgxmanzr42p2bu5ckfqr.streamlit.app",
        "timestamp": "2025-12-27T05:05:28.298740",
        "attempts": 1,
        "status": "ALREADY_RUNNING",
        "message": "App is already running"
      }
    ]
  },
  {
    "execution_time": "2025-12-27T09:22:26.918893",
    "total_apps": 7,
    "results": [
      {
        "name": "TODO アプリ",
        "url": "https://appsimpletodo-nrzgxmanzr42p2bu5ckfqr.streamlit.app",
        "timestamp": "2025-12-27T09:22:02.436304",
        "attempts": 1,
        "status": "ALREADY_RUNNING",
        "message": "App is already running"
      }
    ]
  },
  {
    "execution_time": "2025-12-27T13:14:00.263913",
    "total_apps": 7,
    "results": [
      {
        "name": "TODO アプリ",
        "url": "https://appsimpletodo-nrzgxmanzr42p2bu5ckfqr.streamlit.app",
        "timestamp": "2025-12-27T13:13:35.701879",
        "attempts": 1,
        "status": "ALREADY_RUNNING",
        "message": "App is already running"
      }
    ]
  },
  {
    "execution_time": "2025-12-27T17:07:33.416580",
    "total_apps": 7,
    "results": [
      {
        "name": "TODO アプリ",
        "url": "https://appsimpletodo-nrzgxmanzr42p2bu5ckfqr.streamlit.app",
        "timestamp": "2025-12-27T17:07:08.821214",
        "attempts": 1,
        "status": "ALREADY_RUNNING",
        "message": "App is already running"
      }
    ]
  },
  {
    "execution_time": "2025-12-27T21:09:15.955267",
    "total_apps": 7,
    "results": [
      {
        "name": "TODO アプリ",
        "url": "https://appsimpletodo-nrzgxmanzr42p2bu5ckfqr.streamlit.app",
        "timestamp": "2025-12-27T21:08:51.430310",
        "attempts": 1,
        "status": "ALREADY_RUNNING",
        "message": "App is already running"
      }
    ]
  }
]